pointcloudpipeline/__init__.py
pointcloudpipeline/__main__.py
pointcloudpipeline/pipeline_worker.py
pointcloudpipeline/test_pipeline_worker.py
pointcloudpipeline-1.1.2.data/scripts/pipeline_worker.py
pointcloudpipeline-1.1.2.dist-info/LICENSE
pointcloudpipeline-1.1.2.dist-info/METADATA
pointcloudpipeline-1.1.2.dist-info/WHEEL
pointcloudpipeline-1.1.2.dist-info/entry_points.txt
pointcloudpipeline-1.1.2.dist-info/top_level.txt
pointcloudpipeline-1.1.2.dist-info/RECORD
