Metadata-Version: 2.1
Name: pointcloudpipeline
Version: 1.1.2
Summary: A simple commandline app for converting pointclouds and get 2D images out of a pointclouds.
Home-page: UNKNOWN
Author: Nadine Sennhauser and Denis Nauli
Author-email: nadine.sennhauser@ost.ch
License: BSD-2
Keywords: pointcloud,convert,pointcloudbrowser
Platform: UNKNOWN
Classifier: Programming Language :: Python :: 3
Requires-Python: >=3.1
Requires-Dist: click
Requires-Dist: cython
Requires-Dist: numpy
Requires-Dist: packaging
Requires-Dist: pdal
Requires-Dist: scikit-build
